EmberJsRumenjiaochengBowenHuizong/README.md
EmberJsRumenjiaochengBowenHuizong/__init__.py
EmberJsRumenjiaochengBowenHuizong/__main__.py
EmberJsRumenjiaochengBowenHuizong/file.epub
EmberJsRumenjiaochengBowenHuizong/index.html
EmberJsRumenjiaochengBowenHuizong/css/__init__.py
EmberJsRumenjiaochengBowenHuizong/css/annotations.css
EmberJsRumenjiaochengBowenHuizong/css/main.css
EmberJsRumenjiaochengBowenHuizong/css/normalize.css
EmberJsRumenjiaochengBowenHuizong/css/popup.css
EmberJsRumenjiaochengBowenHuizong/font/__init__.py
EmberJsRumenjiaochengBowenHuizong/font/fontello.eot
EmberJsRumenjiaochengBowenHuizong/font/fontello.svg
EmberJsRumenjiaochengBowenHuizong/font/fontello.ttf
EmberJsRumenjiaochengBowenHuizong/font/fontello.woff
EmberJsRumenjiaochengBowenHuizong/img/__init__.py
EmberJsRumenjiaochengBowenHuizong/img/annotator-glyph-sprite.png
EmberJsRumenjiaochengBowenHuizong/img/annotator-icon-sprite.png
EmberJsRumenjiaochengBowenHuizong/img/apple-touch-icon.png
EmberJsRumenjiaochengBowenHuizong/img/cancelfullscreen.png
EmberJsRumenjiaochengBowenHuizong/img/close.png
EmberJsRumenjiaochengBowenHuizong/img/fullscreen.png
EmberJsRumenjiaochengBowenHuizong/img/loader.gif
EmberJsRumenjiaochengBowenHuizong/img/menu-icon.png
EmberJsRumenjiaochengBowenHuizong/img/save.png
EmberJsRumenjiaochengBowenHuizong/img/saved.png
EmberJsRumenjiaochengBowenHuizong/img/settings-s.png
EmberJsRumenjiaochengBowenHuizong/img/settings.png
EmberJsRumenjiaochengBowenHuizong/img/star.png
EmberJsRumenjiaochengBowenHuizong/js/__init__.py
EmberJsRumenjiaochengBowenHuizong/js/epub.js
EmberJsRumenjiaochengBowenHuizong/js/epub.min.js
EmberJsRumenjiaochengBowenHuizong/js/epub.min.map
EmberJsRumenjiaochengBowenHuizong/js/hooks.min.js
EmberJsRumenjiaochengBowenHuizong/js/hooks.min.map
EmberJsRumenjiaochengBowenHuizong/js/reader.js
EmberJsRumenjiaochengBowenHuizong/js/reader.js.map
EmberJsRumenjiaochengBowenHuizong/js/reader.min.js
EmberJsRumenjiaochengBowenHuizong/js/reader.min.map
ember_js_rumenjiaocheng_bowen_huizong-2024.3.2.0.dist-info/METADATA
ember_js_rumenjiaocheng_bowen_huizong-2024.3.2.0.dist-info/WHEEL
ember_js_rumenjiaocheng_bowen_huizong-2024.3.2.0.dist-info/entry_points.txt
ember_js_rumenjiaocheng_bowen_huizong-2024.3.2.0.dist-info/top_level.txt
ember_js_rumenjiaocheng_bowen_huizong-2024.3.2.0.dist-info/RECORD
